[
	{
		"id": "63bd7a2a7a901dbf79c27bac",
		"title": "Camera",
		"picture": "https://i.ibb.co/wdMD6dQ/product-1.jpg",
		"quantity": 1,
		"sizes_color": false,
		"ratings": 5,
		"price": 600,
		"stockAmount": 10,
		"category": "Electronics"
	},
	{
		"id": "63bd7a2afe3a00a5df1dff69",
		"title": "Shirt",
		"picture": "https://i.ibb.co/H2jPCH2/product-2.jpg",
		"quantity": 1,
		"sizes_color": true,
		"ratings": 4.5,
		"price": 200,
		"stockAmount": 3,
		"category": "Fashion"
	},
	{
		"id": "63bd7a2a1d1dfe06d8f7b1a1",
		"title": "Lamp",
		"picture": "https://i.ibb.co/ydh9p5d/product-3.jpg",
		"quantity": 1,
		"sizes_color": false,
		"ratings": 5,
		"price": 298,
		"stockAmount": 32,
		"category": "Home Decor"
	},
	{
		"id": "63bd7a2a1fb9930c828ac600",
		"title": "Shoes",
		"picture": "https://i.ibb.co/ZM0QsM1/product-4.jpg",
		"quantity": 1,
		"sizes_color": true,
		"ratings": 3.5,
		"price": 398,
		"stockAmount": 20,
		"category": "Fashion"
	},
	{
		"id": "63bd7a2afa1aa2dc6786124b",
		"title": "Drone",
		"picture": "https://i.ibb.co/hXtxKr8/product-5.jpg",
		"quantity": 1,
		"sizes_color": false,
		"ratings": 4.5,
		"price": 1000,
		"stockAmount": 5,
		"category": "Electronics"
	},
	{
		"id": "63bd7a2af068bb9b1f3adc88",
		"title": "Watch",
		"picture": "https://i.ibb.co/KNkTrLC/product-6.jpg",
		"quantity": 1,
		"sizes_color": true,
		"ratings": 5,
		"price": 400,
		"stockAmount": 24,
		"category": "Electronics"
	},
	{
		"id": "63bd7a2a409f2895d4c844c8",
		"title": "Dress",
		"picture": "https://i.ibb.co/3czPjPz/product-7.jpg",
		"quantity": 1,
		"sizes_color": true,
		"ratings": 4,
		"price": 200,
		"stockAmount": 50,
		"category": "Fashion"
	},
	{
		"id": "63bd7a2aca9c060879e0ce00",
		"title": "Facial Cream",
		"picture": "https://i.ibb.co/LzkZKVz/product-8.jpg",
		"quantity": 1,
		"sizes_color": false,
		"ratings": 5,
		"price": 120,
		"stockAmount": 200,
		"category": "Cosmetics"
	},
	{
		"id": "63c6653f4a77fe583c029130",
		"title": "Chair",
		"picture": "https://i.ibb.co/Bt8cMrs/product-9.jpg",
		"quantity": 1,
		"sizes_color": true,
		"ratings": 4,
		"price": 700,
		"stockAmount": 1,
		"category": "Home Decor"
	}
]
